.gitignore
CONTRIBUTING.md
LICENSE
Makefile
README.md
config.ini
pyproject.toml
requirements.txt
setup.py
.github/dependabot.yml
.github/ISSUE_TEMPLATE/bug_report.md
.github/ISSUE_TEMPLATE/feature_request.md
.github/workflows/build.yml
action_react/__init__.py
action_react/main.py
action_react/react.py
action_react.egg-info/PKG-INFO
action_react.egg-info/SOURCES.txt
action_react.egg-info/dependency_links.txt
action_react.egg-info/requires.txt
action_react.egg-info/top_level.txt
action_react/tests/test_all.py
action_react/tests/fixtures/config.ini
docs/Makefile
docs/conf.py
docs/index.md
docs/make.bat